django_jackfrost-0.4.0.dist-info/DESCRIPTION.rst
django_jackfrost-0.4.0.dist-info/LICENSE.txt
django_jackfrost-0.4.0.dist-info/METADATA
django_jackfrost-0.4.0.dist-info/metadata.json
django_jackfrost-0.4.0.dist-info/RECORD
django_jackfrost-0.4.0.dist-info/top_level.txt
django_jackfrost-0.4.0.dist-info/WHEEL
jackfrost/__init__.py
jackfrost/actions.py
jackfrost/apps.py
jackfrost/checks.py
jackfrost/defaults.py
jackfrost/models.py
jackfrost/README.rst
jackfrost/signals.py
jackfrost/tasks.py
jackfrost/test_actions.py
jackfrost/test_celery.py
jackfrost/test_checks.py
jackfrost/test_command.py
jackfrost/test_modelrenderer.py
jackfrost/test_urlcollector.py
jackfrost/test_urlcollector_feed.py
jackfrost/test_urlcollector_medusa.py
jackfrost/test_urlcollector_sitemap.py
jackfrost/test_urlreader.py
jackfrost/test_urlwriter.py
jackfrost/test_utils_eventlog.py
jackfrost/test_utils_presave_postsave.py
jackfrost/utils.py
jackfrost/management/__init__.py
jackfrost/management/README.rst
jackfrost/management/commands/__init__.py
jackfrost/management/commands/collectstaticsite.py
jackfrost/management/commands/README.rst
jackfrost/templates/301.html
jackfrost/templates/jackfrost/build_selected_confirmation.html
