Metadata-Version: 2.0
Name: django-jackfrost
Version: 0.4.0
Summary: A static site generator for Django views
Home-page: https://github.com/kezabelle/django-jackfrost
Author: Keryn Knight
Author-email: python-package@kerynknight.com
License: BSD License
Download-URL: https://github.com/kezabelle/django-jackfrost/releases
Keywords: django,static,freeze,generator
Platform: UNKNOWN
Classifier: Development Status :: 4 - Beta
Classifier: Intended Audience :: Developers
Classifier: License :: OSI Approved :: BSD License
Classifier: Environment :: Web Environment
Classifier: Topic :: Internet :: WWW/HTTP
Classifier: Programming Language :: Python
Classifier: Programming Language :: Python :: 2
Classifier: Programming Language :: Python :: 2.7
Classifier: Programming Language :: Python :: 3
Classifier: Programming Language :: Python :: 3.3
Classifier: Programming Language :: Python :: 3.4
Classifier: Framework :: Django
Classifier: Framework :: Django :: 1.5
Classifier: Framework :: Django :: 1.6
Classifier: Framework :: Django :: 1.7
Classifier: Framework :: Django :: 1.8
Requires-Dist: Django (>=1.5)
